sqlcli/__init__.py
sqlcli/api.py
sqlcli/cli.py
sqlcli/core/__init__.py
sqlcli/core/alembic.ini
sqlcli/core/catalog.py
sqlcli/core/connection.py
sqlcli/core/database.py
sqlcli/core/migrations/README
sqlcli/core/migrations/__init__.py
sqlcli/core/migrations/env.py
sqlcli/core/migrations/script.py.mako
sqlcli/core/migrations/versions/44da61dbd8d2_create_catalog_tables.py
sqlcli/core/records.py
sqlcli/settings.py
sqlcli_sh-0.1.0.dist-info/LICENSE
sqlcli_sh-0.1.0.dist-info/METADATA
sqlcli_sh-0.1.0.dist-info/WHEEL
sqlcli_sh-0.1.0.dist-info/entry_points.txt
sqlcli_sh-0.1.0.dist-info/RECORD
