Metadata-Version: 2.1
Name: sqlcli.sh
Version: 0.1.0
Summary: A SQL IDE in your terminal
Home-page: https://github.com/sqlcli-sh/sqlcli.sh
Author: vrajat
Author-email: info@sqlcli.sh
Requires-Python: >=3.8,<4.0
Classifier: Programming Language :: Python :: 3
Classifier: Programming Language :: Python :: 3.8
Classifier: Programming Language :: Python :: 3.9
Classifier: Programming Language :: Python :: 3.10
Classifier: Programming Language :: Python :: 3.11
Classifier: Programming Language :: Python :: 3.12
Requires-Dist: alembic (>=1.12.1,<2.0.0)
Requires-Dist: names-generator (>=0.1.0,<0.2.0)
Requires-Dist: pydantic (>=1.10.7)
Requires-Dist: rich (>=13.7.0,<14.0.0)
Requires-Dist: sqlalchemy (>=2.0.23,<3.0.0)
Requires-Dist: sqlalchemy-mixins (>=2.0.5,<3.0.0)
Requires-Dist: typer[all] (>=0.9.0)
Project-URL: Repository, https://github.com/sqlcli-sh/sqlcli.sh
